systemslink_python/__init__.py
systemslink_python-0.1.3.dist-info/METADATA
systemslink_python-0.1.3.dist-info/WHEEL
systemslink_python-0.1.3.dist-info/licenses/LICENCE
systemslink_python-0.1.3.dist-info/RECORD
