Metadata-Version: 2.4
Name: systemslink_python
Version: 0.1.3
Summary: A small python interface for interacting with a SystemsLink energy management system.
Project-URL: Homepage, https://gitlab.com/Lime-Parallelogram/systemslink-python
Project-URL: Issues, https://gitlab.com/Lime-Parallelogram/systemslink-python/-/issues
Author-email: Will Hall <public.me@limeparallelogram.uk>
License-File: LICENCE
Classifier: License :: OSI Approved :: MIT License
Classifier: Operating System :: OS Independent
Classifier: Programming Language :: Python :: 3
Requires-Python: >=3.8
Requires-Dist: openpyxl
Requires-Dist: requests
